lmcv_tools/__init__.py
lmcv_tools/__main__.py
lmcv_tools/commands/__init__.py
lmcv_tools/commands/change.py
lmcv_tools/commands/extract.py
lmcv_tools/commands/generate.py
lmcv_tools/commands/help.py
lmcv_tools/commands/reorder.py
lmcv_tools/commands/translate.py
lmcv_tools/interface/__init__.py
lmcv_tools/interface/core.py
lmcv_tools/interface/filer.py
lmcv_tools/interface/messenger.py
lmcv_tools/interface/searcher.py
lmcv_tools/models/__init__.py
lmcv_tools/models/ansi_style.py
lmcv_tools/models/artifacts.py
lmcv_tools/models/custom_errors.py
lmcv_tools/models/extraction_components.py
lmcv_tools/models/geometry.py
lmcv_tools/models/graphics.py
lmcv_tools/models/interpreters.py
lmcv_tools/models/math.py
lmcv_tools/models/simulation.py
lmcv_tools/resources/__init__.py
lmcv_tools/resources/databases/__init__.py
lmcv_tools/resources/databases/extraction_attributes.json
lmcv_tools/resources/databases/help_messages.json
lmcv_tools/resources/databases/translation_reference.json
lmcv_tools/resources/shared/CMakeLists.txt
lmcv_tools/resources/shared/__init__.py
lmcv_tools/resources/shared/boost.cp310-win_amd64.pyd
lmcv_tools/resources/shared/boost.cpp
lmcv_tools/resources/shared/boost.cpython-310-x86_64-linux-gnu.so
lmcv_tools/resources/shared/build/boost.cpython-310-x86_64-linux-gnu.so
lmcv_tools-0.0.32.dist-info/METADATA
lmcv_tools-0.0.32.dist-info/WHEEL
lmcv_tools-0.0.32.dist-info/entry_points.txt
lmcv_tools-0.0.32.dist-info/licenses/LICENSE
lmcv_tools-0.0.32.dist-info/RECORD
