Metadata-Version: 2.4
Name: lmcv_tools
Version: 0.0.32
Summary: Command line tool that provides useful functionalities to LMCV Members
Project-URL: repository, https://github.com/Dev-Gabriel-Braga/lmcv_tools
Author-email: Dev-Gabriel-Braga <gabriel.braga.matos@gmail.com>
License-Expression: GPL-3.0
License-File: LICENSE
Classifier: Development Status :: 3 - Alpha
Classifier: Environment :: Console
Classifier: Intended Audience :: Science/Research
Classifier: License :: OSI Approved :: GNU General Public License v3 (GPLv3)
Classifier: License :: OSI Approved :: MIT License
Classifier: Operating System :: OS Independent
Classifier: Programming Language :: Python :: 3
Classifier: Topic :: Scientific/Engineering
Requires-Python: >=3.10
